parametric_ttl_cache/__init__.py
parametric_ttl_cache/ttl_cache.py
parametric_ttl_cache-1.0.2.dist-info/METADATA
parametric_ttl_cache-1.0.2.dist-info/WHEEL
parametric_ttl_cache-1.0.2.dist-info/top_level.txt
parametric_ttl_cache-1.0.2.dist-info/RECORD
