Metadata-Version: 2.1
Name: parametric-ttl-cache
Version: 1.0.2
Summary: A function-level memory cache that supports Time To Live (TTL)
Home-page: https://github.com/jogakdal/python_ttl_cache
Author: Yongho Hwang
Author-email: jogakdal@gmail.com
License: UNKNOWN
Keywords: cache,memory cache,ttl cache,function cache,cache decorator,parametric cache,jogakdal
Platform: UNKNOWN
Classifier: Programming Language :: Python :: 3
Classifier: Operating System :: OS Independent
Requires-Python: >=3.6
Requires-Dist: expiringdict
